{
    "@schema": "https://raw.githubusercontent.com/slicer/slicer/master/Modules/Loadable/Markups/Resources/Schema/markups-schema-v1.0.3.json#",
    "markups": [
        {
            "type": "Fiducial",
            "coordinateSystem": "LPS",
            "coordinateUnits": "mm",
            "locked": false,
            "fixedNumberOfControlPoints": false,
            "labelFormat": "%N-%d",
            "lastUsedControlPointNumber": 45,
            "controlPoints": [
                {
                    "id": "vtkMRMLMarkupsFiducialNode_0",
                    "label": "1",
                    "description": "",
                    "associatedNodeID": "",
                    "position": [8.39188, 6.31512, 15.8514],
                    "orientation": [-1.0, -0.0, -0.0, -0.0, -1.0, -0.0, 0.0, 0.0, 1.0],
                    "selected": true,
                    "locked": true,
                    "visibility": true,
                    "positionStatus": "defined"
                },
                {
                    "id": "vtkMRMLMarkupsFiducialNode_1",
                    "label": "2",
                    "description": "",
                    "associatedNodeID": "",
                    "position": [10.4556, 6.98653, 14.8442],
                    "orientation": [-1.0, -0.0, -0.0, -0.0, -1.0, -0.0, 0.0, 0.0, 1.0],
                    "selected": true,
                    "locked": true,
                    "visibility": true,
                    "positionStatus": "defined"
                },
                {
                    "id": "vtkMRMLMarkupsFiducialNode_2",
                    "label": "3",
                    "description": "",
                    "associatedNodeID": "",
                    "position": [8.43295, 8.43329, 14.9883],
                    "orientation": [-1.0, -0.0, -0.0, -0.0, -1.0, -0.0, 0.0, 0.0, 1.0],
                    "selected": true,
                    "locked": true,
                    "visibility": true,
                    "positionStatus": "defined"
                },
                {
                    "id": "vtkMRMLMarkupsFiducialNode_3",
                    "label": "4",
                    "description": "",
                    "associatedNodeID": "",
                    "position": [13.9405, 9.94738, 14.4976],
                    "orientation": [-1.0, -0.0, -0.0, -0.0, -1.0, -0.0, 0.0, 0.0, 1.0],
                    "selected": true,
                    "locked": true,
                    "visibility": true,
                    "positionStatus": "defined"
                },
                {
                    "id": "vtkMRMLMarkupsFiducialNode_4",
                    "label": "5",
                    "description": "",
                    "associatedNodeID": "",
                    "position": [10.824, 12.6227, 14.7799],
                    "orientation": [-1.0, -0.0, -0.0, -0.0, -1.0, -0.0, 0.0, 0.0, 1.0],
                    "selected": true,
                    "locked": true,
                    "visibility": true,
                    "positionStatus": "defined"
                },
                {
                    "id": "vtkMRMLMarkupsFiducialNode_5",
                    "label": "6",
                    "description": "",
                    "associatedNodeID": "",
                    "position": [13.484, 11.6405, 14.8508],
                    "orientation": [-1.0, -0.0, -0.0, -0.0, -1.0, -0.0, 0.0, 0.0, 1.0],
                    "selected": true,
                    "locked": true,
                    "visibility": true,
                    "positionStatus": "defined"
                },
                {
                    "id": "vtkMRMLMarkupsFiducialNode_6",
                    "label": "7",
                    "description": "",
                    "associatedNodeID": "",
                    "position": [12.3254, 12.4003, 14.9563],
                    "orientation": [-1.0, -0.0, -0.0, -0.0, -1.0, -0.0, 0.0, 0.0, 1.0],
                    "selected": true,
                    "locked": true,
                    "visibility": true,
                    "positionStatus": "defined"
                },
                {
                    "id": "vtkMRMLMarkupsFiducialNode_7",
                    "label": "8",
                    "description": "",
                    "associatedNodeID": "",
                    "position": [17.087, 9.13634, 10.3325],
                    "orientation": [-1.0, -0.0, -0.0, -0.0, -1.0, -0.0, 0.0, 0.0, 1.0],
                    "selected": true,
                    "locked": true,
                    "visibility": true,
                    "positionStatus": "defined"
                },
                {
                    "id": "vtkMRMLMarkupsFiducialNode_8",
                    "label": "9",
                    "description": "",
                    "associatedNodeID": "",
                    "position": [8.98741, 15.7825, 10.8287],
                    "orientation": [-1.0, -0.0, -0.0, -0.0, -1.0, -0.0, 0.0, 0.0, 1.0],
                    "selected": true,
                    "locked": true,
                    "visibility": true,
                    "positionStatus": "defined"
                },
                {
                    "id": "vtkMRMLMarkupsFiducialNode_9",
                    "label": "10",
                    "description": "",
                    "associatedNodeID": "",
                    "position": [17.5888, 12.9457, 12.9454],
                    "orientation": [-1.0, -0.0, -0.0, -0.0, -1.0, -0.0, 0.0, 0.0, 1.0],
                    "selected": true,
                    "locked": true,
                    "visibility": true,
                    "positionStatus": "defined"
                },
                {
                    "id": "vtkMRMLMarkupsFiducialNode_10",
                    "label": "11",
                    "description": "",
                    "associatedNodeID": "",
                    "position": [12.8259, 17.0041, 13.2408],
                    "orientation": [-1.0, -0.0, -0.0, -0.0, -1.0, -0.0, 0.0, 0.0, 1.0],
                    "selected": true,
                    "locked": true,
                    "visibility": true,
                    "positionStatus": "defined"
                },
                {
                    "id": "vtkMRMLMarkupsFiducialNode_11",
                    "label": "12",
                    "description": "",
                    "associatedNodeID": "",
                    "position": [19.0644, 10.7985, 8.14891],
                    "orientation": [-1.0, -0.0, -0.0, -0.0, -1.0, -0.0, 0.0, 0.0, 1.0],
                    "selected": true,
                    "locked": true,
                    "visibility": true,
                    "positionStatus": "defined"
                },
                {
                    "id": "vtkMRMLMarkupsFiducialNode_12",
                    "label": "13",
                    "description": "",
                    "associatedNodeID": "",
                    "position": [17.0036, 17.4588, 12.6609],
                    "orientation": [-1.0, -0.0, -0.0, -0.0, -1.0, -0.0, 0.0, 0.0, 1.0],
                    "selected": true,
                    "locked": true,
                    "visibility": true,
                    "positionStatus": "defined"
                },
                {
                    "id": "vtkMRMLMarkupsFiducialNode_13",
                    "label": "14",
                    "description": "",
                    "associatedNodeID": "",
                    "position": [10.0877, 18.4809, 8.81782],
                    "orientation": [-1.0, -0.0, -0.0, -0.0, -1.0, -0.0, 0.0, 0.0, 1.0],
                    "selected": true,
                    "locked": true,
                    "visibility": true,
                    "positionStatus": "defined"
                },
                {
                    "id": "vtkMRMLMarkupsFiducialNode_14",
                    "label": "15",
                    "description": "",
                    "associatedNodeID": "",
                    "position": [22.1532, 16.5123, 7.49858],
                    "orientation": [-1.0, -0.0, -0.0, -0.0, -1.0, -0.0, 0.0, 0.0, 1.0],
                    "selected": true,
                    "locked": true,
                    "visibility": true,
                    "positionStatus": "defined"
                },
                {
                    "id": "vtkMRMLMarkupsFiducialNode_15",
                    "label": "16",
                    "description": "",
                    "associatedNodeID": "",
                    "position": [19.0766, 20.2119, 10.1937],
                    "orientation": [-1.0, -0.0, -0.0, -0.0, -1.0, -0.0, 0.0, 0.0, 1.0],
                    "selected": true,
                    "locked": true,
                    "visibility": true,
                    "positionStatus": "defined"
                },
                {
                    "id": "vtkMRMLMarkupsFiducialNode_16",
                    "label": "17",
                    "description": "",
                    "associatedNodeID": "",
                    "position": [15.195, 22.4866, 8.50139],
                    "orientation": [-1.0, -0.0, -0.0, -0.0, -1.0, -0.0, 0.0, 0.0, 1.0],
                    "selected": true,
                    "locked": true,
                    "visibility": true,
                    "positionStatus": "defined"
                },
                {
                    "id": "vtkMRMLMarkupsFiducialNode_17",
                    "label": "18",
                    "description": "",
                    "associatedNodeID": "",
                    "position": [22.4375, 18.5773, 6.40945],
                    "orientation": [-1.0, -0.0, -0.0, -0.0, -1.0, -0.0, 0.0, 0.0, 1.0],
                    "selected": true,
                    "locked": true,
                    "visibility": true,
                    "positionStatus": "defined"
                },
                {
                    "id": "vtkMRMLMarkupsFiducialNode_18",
                    "label": "19",
                    "description": "",
                    "associatedNodeID": "",
                    "position": [20.6853, 22.1545, 7.41432],
                    "orientation": [-1.0, -0.0, -0.0, -0.0, -1.0, -0.0, 0.0, 0.0, 1.0],
                    "selected": true,
                    "locked": true,
                    "visibility": true,
                    "positionStatus": "defined"
                },
                {
                    "id": "vtkMRMLMarkupsFiducialNode_19",
                    "label": "20",
                    "description": "",
                    "associatedNodeID": "",
                    "position": [16.708, 23.2975, 7.15019],
                    "orientation": [-1.0, -0.0, -0.0, -0.0, -1.0, -0.0, 0.0, 0.0, 1.0],
                    "selected": true,
                    "locked": true,
                    "visibility": true,
                    "positionStatus": "defined"
                },
                {
                    "id": "vtkMRMLMarkupsFiducialNode_20",
                    "label": "21",
                    "description": "",
                    "associatedNodeID": "",
                    "position": [20.1346, 22.023, 4.44529],
                    "orientation": [-1.0, -0.0, -0.0, -0.0, -1.0, -0.0, 0.0, 0.0, 1.0],
                    "selected": true,
                    "locked": true,
                    "visibility": true,
                    "positionStatus": "defined"
                },
                {
                    "id": "vtkMRMLMarkupsFiducialNode_21",
                    "label": "22",
                    "description": "",
                    "associatedNodeID": "",
                    "position": [13.7638, 21.6079, 5.51683],
                    "orientation": [-1.0, -0.0, -0.0, -0.0, -1.0, -0.0, 0.0, 0.0, 1.0],
                    "selected": true,
                    "locked": true,
                    "visibility": true,
                    "positionStatus": "defined"
                },
                {
                    "id": "vtkMRMLMarkupsFiducialNode_22",
                    "label": "24",
                    "description": "",
                    "associatedNodeID": "",
                    "position": [12.7788, 19.9972, 7.33326],
                    "orientation": [-1.0, -0.0, -0.0, -0.0, -1.0, -0.0, 0.0, 0.0, 1.0],
                    "selected": true,
                    "locked": true,
                    "visibility": true,
                    "positionStatus": "defined"
                },
                {
                    "id": "vtkMRMLMarkupsFiducialNode_23",
                    "label": "25",
                    "description": "",
                    "associatedNodeID": "",
                    "position": [21.3715, 15.4049, 4.93316],
                    "orientation": [-1.0, -0.0, -0.0, -0.0, -1.0, -0.0, 0.0, 0.0, 1.0],
                    "selected": true,
                    "locked": true,
                    "visibility": true,
                    "positionStatus": "defined"
                },
                {
                    "id": "vtkMRMLMarkupsFiducialNode_24",
                    "label": "27",
                    "description": "",
                    "associatedNodeID": "",
                    "position": [20.0218, 14.1495, 6.69146],
                    "orientation": [-1.0, -0.0, -0.0, -0.0, -1.0, -0.0, 0.0, 0.0, 1.0],
                    "selected": true,
                    "locked": true,
                    "visibility": true,
                    "positionStatus": "defined"
                },
                {
                    "id": "vtkMRMLMarkupsFiducialNode_25",
                    "label": "28",
                    "description": "",
                    "associatedNodeID": "",
                    "position": [7.80125, 5.89501, 13.2634],
                    "orientation": [-1.0, -0.0, -0.0, -0.0, -1.0, -0.0, 0.0, 0.0, 1.0],
                    "selected": true,
                    "locked": true,
                    "visibility": true,
                    "positionStatus": "defined"
                },
                {
                    "id": "vtkMRMLMarkupsFiducialNode_26",
                    "label": "29",
                    "description": "",
                    "associatedNodeID": "",
                    "position": [8.93741, 7.30281, 12.2303],
                    "orientation": [-1.0, -0.0, -0.0, -0.0, -1.0, -0.0, 0.0, 0.0, 1.0],
                    "selected": true,
                    "locked": true,
                    "visibility": true,
                    "positionStatus": "defined"
                },
                {
                    "id": "vtkMRMLMarkupsFiducialNode_27",
                    "label": "30",
                    "description": "",
                    "associatedNodeID": "",
                    "position": [9.10213, 8.02388, 11.9765],
                    "orientation": [-1.0, -0.0, -0.0, -0.0, -1.0, -0.0, 0.0, 0.0, 1.0],
                    "selected": true,
                    "locked": true,
                    "visibility": true,
                    "positionStatus": "defined"
                },
                {
                    "id": "vtkMRMLMarkupsFiducialNode_28",
                    "label": "31",
                    "description": "",
                    "associatedNodeID": "",
                    "position": [9.58342, 7.63222, 11.9611],
                    "orientation": [-1.0, -0.0, -0.0, -0.0, -1.0, -0.0, 0.0, 0.0, 1.0],
                    "selected": true,
                    "locked": true,
                    "visibility": true,
                    "positionStatus": "defined"
                },
                {
                    "id": "vtkMRMLMarkupsFiducialNode_29",
                    "label": "32",
                    "description": "",
                    "associatedNodeID": "",
                    "position": [9.36789, 9.63427, 11.2203],
                    "orientation": [-1.0, -0.0, -0.0, -0.0, -1.0, -0.0, 0.0, 0.0, 1.0],
                    "selected": true,
                    "locked": true,
                    "visibility": true,
                    "positionStatus": "defined"
                },
                {
                    "id": "vtkMRMLMarkupsFiducialNode_30",
                    "label": "33",
                    "description": "",
                    "associatedNodeID": "",
                    "position": [11.1226, 8.2554, 11.0945],
                    "orientation": [-1.0, -0.0, -0.0, -0.0, -1.0, -0.0, 0.0, 0.0, 1.0],
                    "selected": true,
                    "locked": true,
                    "visibility": true,
                    "positionStatus": "defined"
                },
                {
                    "id": "vtkMRMLMarkupsFiducialNode_31",
                    "label": "36",
                    "description": "",
                    "associatedNodeID": "",
                    "position": [10.064, 11.7146, 10.1619],
                    "orientation": [-1.0, -0.0, -0.0, -0.0, -1.0, -0.0, 0.0, 0.0, 1.0],
                    "selected": true,
                    "locked": true,
                    "visibility": true,
                    "positionStatus": "defined"
                },
                {
                    "id": "vtkMRMLMarkupsFiducialNode_32",
                    "label": "37",
                    "description": "",
                    "associatedNodeID": "",
                    "position": [12.8222, 9.52571, 9.95087],
                    "orientation": [-1.0, -0.0, -0.0, -0.0, -1.0, -0.0, 0.0, 0.0, 1.0],
                    "selected": true,
                    "locked": true,
                    "visibility": true,
                    "positionStatus": "defined"
                },
                {
                    "id": "vtkMRMLMarkupsFiducialNode_33",
                    "label": "38",
                    "description": "",
                    "associatedNodeID": "",
                    "position": [11.7595, 11.6457, 9.84442],
                    "orientation": [-1.0, -0.0, -0.0, -0.0, -1.0, -0.0, 0.0, 0.0, 1.0],
                    "selected": true,
                    "locked": true,
                    "visibility": true,
                    "positionStatus": "defined"
                },
                {
                    "id": "vtkMRMLMarkupsFiducialNode_34",
                    "label": "39",
                    "description": "",
                    "associatedNodeID": "",
                    "position": [12.3867, 11.0892, 9.80915],
                    "orientation": [-1.0, -0.0, -0.0, -0.0, -1.0, -0.0, 0.0, 0.0, 1.0],
                    "selected": true,
                    "locked": true,
                    "visibility": true,
                    "positionStatus": "defined"
                },
                {
                    "id": "vtkMRMLMarkupsFiducialNode_35",
                    "label": "40",
                    "description": "",
                    "associatedNodeID": "",
                    "position": [12.3332, 12.7713, 8.63097],
                    "orientation": [-1.0, -0.0, -0.0, -0.0, -1.0, -0.0, 0.0, 0.0, 1.0],
                    "selected": true,
                    "locked": true,
                    "visibility": true,
                    "positionStatus": "defined"
                },
                {
                    "id": "vtkMRMLMarkupsFiducialNode_36",
                    "label": "41",
                    "description": "",
                    "associatedNodeID": "",
                    "position": [13.3357, 12.093, 8.62832],
                    "orientation": [-1.0, -0.0, -0.0, -0.0, -1.0, -0.0, 0.0, 0.0, 1.0],
                    "selected": true,
                    "locked": true,
                    "visibility": true,
                    "positionStatus": "defined"
                },
                {
                    "id": "vtkMRMLMarkupsFiducialNode_37",
                    "label": "42",
                    "description": "",
                    "associatedNodeID": "",
                    "position": [12.1969, 14.2175, 7.86873],
                    "orientation": [-1.0, -0.0, -0.0, -0.0, -1.0, -0.0, 0.0, 0.0, 1.0],
                    "selected": true,
                    "locked": true,
                    "visibility": true,
                    "positionStatus": "defined"
                },
                {
                    "id": "vtkMRMLMarkupsFiducialNode_38",
                    "label": "43",
                    "description": "",
                    "associatedNodeID": "",
                    "position": [14.5889, 12.0792, 7.58654],
                    "orientation": [-1.0, -0.0, -0.0, -0.0, -1.0, -0.0, 0.0, 0.0, 1.0],
                    "selected": true,
                    "locked": true,
                    "visibility": true,
                    "positionStatus": "defined"
                },
                {
                    "id": "vtkMRMLMarkupsFiducialNode_39",
                    "label": "44",
                    "description": "",
                    "associatedNodeID": "",
                    "position": [13.6137, 13.5843, 7.1682],
                    "orientation": [-1.0, -0.0, -0.0, -0.0, -1.0, -0.0, 0.0, 0.0, 1.0],
                    "selected": true,
                    "locked": true,
                    "visibility": true,
                    "positionStatus": "defined"
                },
                {
                    "id": "vtkMRMLMarkupsFiducialNode_40",
                    "label": "46",
                    "description": "",
                    "associatedNodeID": "",
                    "position": [15.309, 17.3825, 5.00277],
                    "orientation": [-1.0, -0.0, -0.0, -0.0, -1.0, -0.0, 0.0, 0.0, 1.0],
                    "selected": true,
                    "locked": true,
                    "visibility": true,
                    "positionStatus": "defined"
                },
                {
                    "id": "vtkMRMLMarkupsFiducialNode_41",
                    "label": "47",
                    "description": "",
                    "associatedNodeID": "",
                    "position": [16.7688, 16.248, 4.87523],
                    "orientation": [-1.0, -0.0, -0.0, -0.0, -1.0, -0.0, 0.0, 0.0, 1.0],
                    "selected": true,
                    "locked": true,
                    "visibility": true,
                    "positionStatus": "defined"
                },
                {
                    "id": "vtkMRMLMarkupsFiducialNode_42",
                    "label": "49",
                    "description": "",
                    "associatedNodeID": "",
                    "position": [19.8562, 18.0981, 3.08795],
                    "orientation": [-1.0, -0.0, -0.0, -0.0, -1.0, -0.0, 0.0, 0.0, 1.0],
                    "selected": true,
                    "locked": true,
                    "visibility": true,
                    "positionStatus": "defined"
                },
                {
                    "id": "vtkMRMLMarkupsFiducialNode_43",
                    "label": "50",
                    "description": "",
                    "associatedNodeID": "",
                    "position": [17.5153, 18.9892, 3.01681],
                    "orientation": [-1.0, -0.0, -0.0, -0.0, -1.0, -0.0, 0.0, 0.0, 1.0],
                    "selected": true,
                    "locked": true,
                    "visibility": true,
                    "positionStatus": "defined"
                },
                {
                    "id": "vtkMRMLMarkupsFiducialNode_44",
                    "label": "51",
                    "description": "",
                    "associatedNodeID": "",
                    "position": [13.2995, 12.477, 14.1044],
                    "orientation": [-1.0, -0.0, -0.0, -0.0, -1.0, -0.0, 0.0, 0.0, 1.0],
                    "selected": true,
                    "locked": true,
                    "visibility": true,
                    "positionStatus": "defined"
                }
            ],
            "measurements": [],
            "display": {
                "visibility": true,
                "opacity": 1.0,
                "color": [0.4, 1.0, 1.0],
                "selectedColor": [1.0, 0.5000076295109483, 0.5000076295109483],
                "activeColor": [0.4, 1.0, 0.0],
                "propertiesLabelVisibility": false,
                "pointLabelsVisibility": true,
                "textScale": 3.0,
                "glyphType": "Sphere3D",
                "glyphScale": 3.0,
                "glyphSize": 5.0,
                "useGlyphScale": true,
                "sliceProjection": false,
                "sliceProjectionUseFiducialColor": true,
                "sliceProjectionOutlinedBehindSlicePlane": false,
                "sliceProjectionColor": [1.0, 1.0, 1.0],
                "sliceProjectionOpacity": 0.6,
                "lineThickness": 0.2,
                "lineColorFadingStart": 1.0,
                "lineColorFadingEnd": 10.0,
                "lineColorFadingSaturation": 1.0,
                "lineColorFadingHueOffset": 0.0,
                "handlesInteractive": false,
                "translationHandleVisibility": true,
                "rotationHandleVisibility": true,
                "scaleHandleVisibility": false,
                "interactionHandleScale": 3.0,
                "snapMode": "toVisibleSurface"
            }
        }
    ]
}